xatra/__init__.py
xatra/data/Loka.py
xatra/data/Varuna.py
xatra/data/__init__.py
xatra/data/break_CHN.28_1_3.json
xatra/data/break_IND.20.20_1_3.json
xatra/data/data.py
xatra/data/feature_AFG_2.json
xatra/data/feature_ALB_0.json
xatra/data/feature_ALB_1.json
xatra/data/feature_ARE_1.json
xatra/data/feature_ARE_2.json
xatra/data/feature_ARM_1.json
xatra/data/feature_AZE_1.json
xatra/data/feature_BGD_2.json
xatra/data/feature_BHR_0.json
xatra/data/feature_BHR_1.json
xatra/data/feature_BIH_0.json
xatra/data/feature_BIH_1.json
xatra/data/feature_BRN_1.json
xatra/data/feature_BRN_2.json
xatra/data/feature_BTN_2.json
xatra/data/feature_CHN_2.json
xatra/data/feature_CYP_0.json
xatra/data/feature_CYP_1.json
xatra/data/feature_DJI_0.json
xatra/data/feature_DJI_1.json
xatra/data/feature_DJI_2.json
xatra/data/feature_DZA_1.json
xatra/data/feature_DZA_2.json
xatra/data/feature_EGY_1.json
xatra/data/feature_EGY_2.json
xatra/data/feature_ERI_0.json
xatra/data/feature_ERI_1.json
xatra/data/feature_ERI_2.json
xatra/data/feature_ESP_1.json
xatra/data/feature_ESP_2.json
xatra/data/feature_FRA_1.json
xatra/data/feature_FRA_2.json
xatra/data/feature_GEO_1.json
xatra/data/feature_GRC_2.json
xatra/data/feature_HRV_0.json
xatra/data/feature_HRV_1.json
xatra/data/feature_IDN_1.json
xatra/data/feature_IDN_2.json
xatra/data/feature_IND_2.json
xatra/data/feature_IRN_2.json
xatra/data/feature_IRQ_1.json
xatra/data/feature_IRQ_2.json
xatra/data/feature_ISR_1.json
xatra/data/feature_ITA_2.json
xatra/data/feature_JOR_1.json
xatra/data/feature_JOR_2.json
xatra/data/feature_JPN_1.json
xatra/data/feature_KAZ_2.json
xatra/data/feature_KGZ_2.json
xatra/data/feature_KHM_1.json
xatra/data/feature_KHM_2.json
xatra/data/feature_KOR_1.json
xatra/data/feature_KWT_0.json
xatra/data/feature_KWT_1.json
xatra/data/feature_LAO_1.json
xatra/data/feature_LAO_2.json
xatra/data/feature_LBN_1.json
xatra/data/feature_LBN_2.json
xatra/data/feature_LBY_1.json
xatra/data/feature_LKA_2.json
xatra/data/feature_MAR_1.json
xatra-0.1.13.dist-info/METADATA
xatra-0.1.13.dist-info/WHEEL
xatra-0.1.13.dist-info/RECORD
