Metadata-Version: 2.1
Name: xatra
Version: 0.1.13
Summary: Xatra (pronounced kshatra), a tool for making historical maps -- the data I have is currently focused on India, but I welcome expansions to the library.
License: MIT
Author: srajma
Author-email: srimahalingam@protonmail.com
Requires-Python: >=3.9,<4.0
Classifier: License :: OSI Approved :: MIT License
Classifier: Programming Language :: Python :: 3
Classifier: Programming Language :: Python :: 3.9
Classifier: Programming Language :: Python :: 3.10
Classifier: Programming Language :: Python :: 3.11
Classifier: Programming Language :: Python :: 3.12
Classifier: Programming Language :: Python :: 3.13
Requires-Dist: folium (>=0.16.0,<0.17.0)
Requires-Dist: geopandas (>=0.14.3,<0.15.0)
Requires-Dist: importlib (>=1.0.4,<2.0.0)
Requires-Dist: matplotlib (>=3.8.3,<4.0.0)
Requires-Dist: overpy (>=0.7,<0.8)
Requires-Dist: requests (>=2.31.0,<3.0.0)
Requires-Dist: topojson (>=1.0,<2.0)
